achakra/__init__.py
achakra/__main__.py
achakra/achakra.py
achakra/api.py
tdm_aneesh-0.1.4.dist-info/.ipynb_checkpoints/SOURCES-checkpoint.txt
tdm_aneesh-0.1.4.dist-info/.ipynb_checkpoints/dependency_links-checkpoint.txt
tdm_aneesh-0.1.4.dist-info/.ipynb_checkpoints/requires-checkpoint.txt
tdm_aneesh-0.1.4.dist-info/.ipynb_checkpoints/top_level-checkpoint.txt
tdm_aneesh-0.1.4.dist-info/LICENSE
tdm_aneesh-0.1.4.dist-info/METADATA
tdm_aneesh-0.1.4.dist-info/WHEEL
tdm_aneesh-0.1.4.dist-info/entry_points.txt
tdm_aneesh-0.1.4.dist-info/top_level.txt
tdm_aneesh-0.1.4.dist-info/RECORD
