Metadata-Version: 2.1
Name: tdm-aneesh
Version: 0.1.4
Summary: Using a virtual environment, creating package
Author: Aneesh Chakravarthula
Author-email: Aneesh Chakravarthula <chakra55@purdue.edu>
License: MIT License
Keywords: example,achakra,tutorial,build
Classifier: License :: OSI Approved :: MIT License
Classifier: Programming Language :: Python
Classifier: Programming Language :: Python :: 3
Classifier: Framework :: FastAPI
Requires-Python: >=3.10
License-File: LICENSE
Requires-Dist: lxml (>=4.9.1)
Requires-Dist: requests (>=2.28.1)
Requires-Dist: fastapi (>=0.85.2)
Requires-Dist: Jinja2 (>=3.1.2)
Requires-Dist: uvicorn[standard]
